odoo8_addon_website_calendar_snippet-8.0.1.0.0.99.dev18-py2.7-nspkg.pth
odoo8_addon_website_calendar_snippet-8.0.1.0.0.99.dev18.dist-info/DESCRIPTION.rst
odoo8_addon_website_calendar_snippet-8.0.1.0.0.99.dev18.dist-info/METADATA
odoo8_addon_website_calendar_snippet-8.0.1.0.0.99.dev18.dist-info/RECORD
odoo8_addon_website_calendar_snippet-8.0.1.0.0.99.dev18.dist-info/WHEEL
odoo8_addon_website_calendar_snippet-8.0.1.0.0.99.dev18.dist-info/metadata.json
odoo8_addon_website_calendar_snippet-8.0.1.0.0.99.dev18.dist-info/namespace_packages.txt
odoo8_addon_website_calendar_snippet-8.0.1.0.0.99.dev18.dist-info/top_level.txt
odoo_addons/website_calendar_snippet/README.rst
odoo_addons/website_calendar_snippet/__init__.py
odoo_addons/website_calendar_snippet/__openerp__.py
odoo_addons/website_calendar_snippet/controllers/__init__.py
odoo_addons/website_calendar_snippet/controllers/main.py
odoo_addons/website_calendar_snippet/i18n/ca.po
odoo_addons/website_calendar_snippet/i18n/de.po
odoo_addons/website_calendar_snippet/i18n/es.po
odoo_addons/website_calendar_snippet/i18n/eu.po
odoo_addons/website_calendar_snippet/i18n/fi.po
odoo_addons/website_calendar_snippet/i18n/fr.po
odoo_addons/website_calendar_snippet/i18n/hr.po
odoo_addons/website_calendar_snippet/i18n/id.po
odoo_addons/website_calendar_snippet/i18n/it.po
odoo_addons/website_calendar_snippet/i18n/nb.po
odoo_addons/website_calendar_snippet/i18n/nl.po
odoo_addons/website_calendar_snippet/i18n/pt_BR.po
odoo_addons/website_calendar_snippet/i18n/sl.po
odoo_addons/website_calendar_snippet/i18n/website_calendar_snippet.pot
odoo_addons/website_calendar_snippet/i18n/zh_CN.po
odoo_addons/website_calendar_snippet/security/ir.model.access.csv
odoo_addons/website_calendar_snippet/security/security.xml
odoo_addons/website_calendar_snippet/static/description/icon.png
odoo_addons/website_calendar_snippet/static/lib/date/js/date.js
odoo_addons/website_calendar_snippet/static/lib/fullcalendar/license.txt
odoo_addons/website_calendar_snippet/static/lib/fullcalendar/css/fullcalendar.css
odoo_addons/website_calendar_snippet/static/lib/fullcalendar/js/fullcalendar.js
odoo_addons/website_calendar_snippet/static/src/css/website_calendar_block.css
odoo_addons/website_calendar_snippet/static/src/img/blocks/calendar.png
odoo_addons/website_calendar_snippet/static/src/js/website_calendar_block.js
odoo_addons/website_calendar_snippet/templates/website_calendar_snippet.xml
